MANIFEST.in
README.txt
setup.py
doc/CHANGES.txt
fassembler_boot/__init__.py
fassembler_boot/config.py
fassembler_boot/newbuild.py
fassembler_boot/newbuild.sh
fassembler_boot/newsite.py
fassembler_boot/opencore.conf
opencore_fassembler_boot.egg-info/PKG-INFO
opencore_fassembler_boot.egg-info/SOURCES.txt
opencore_fassembler_boot.egg-info/dependency_links.txt
opencore_fassembler_boot.egg-info/entry_points.txt
opencore_fassembler_boot.egg-info/not-zip-safe
opencore_fassembler_boot.egg-info/requires.txt
opencore_fassembler_boot.egg-info/top_level.txt