Metadata-Version: 1.0
Name: opencore-fassembler-boot
Version: 0.7.2
Summary: Creates a setup for new OpenCore site deployments that use Fassembler
Home-page: http://www.coactivate.org/projects/opencore
Author: opencore-dev
Author-email: opencore-dev@lists.coactivate.org
License: GPLv3
Platform: UNKNOWN
